<annotation>
	<folder></folder>
	<filename>im250_jpg.rf.c752af7e193759ffbf9a4df1b6b86d55.jpg</filename>
	<path>im250_jpg.rf.c752af7e193759ffbf9a4df1b6b86d55.jpg</path>
	<source>
		<database>roboflow.com</database>
	</source>
	<size>
		<width>640</width>
		<height>640</height>
		<depth>3</depth>
	</size>
	<segmented>0</segmented>
	<object>
		<name>dent</name>
		<pose>Unspecified</pose>
		<truncated>0</truncated>
		<difficult>0</difficult>
		<occluded>0</occluded>
		<bndbox>
			<xmin>287</xmin>
			<xmax>351</xmax>
			<ymin>320</ymin>
			<ymax>341</ymax>
		</bndbox>
		<polygon>
			<x1>338.962962</x1>
			<y1>339.777778</y1>
			<x2>349.62963</x2>
			<y2>339.777778</y2>
			<x3>322.37037</x3>
			<y3>328</y3>
			<x4>290.37037</x4>
			<y4>318.888888</y4>
			<x5>286.024692</x5>
			<y5>323.333334</y5>
			<x6>316.049382</x6>
			<y6>329.333334</y6>
			<x7>338.962962</x7>
			<y7>339.777778</y7>
		</polygon>
	</object>
	<object>
		<name>dent</name>
		<pose>Unspecified</pose>
		<truncated>0</truncated>
		<difficult>0</difficult>
		<occluded>0</occluded>
		<bndbox>
			<xmin>223</xmin>
			<xmax>325</xmax>
			<ymin>398</ymin>
			<ymax>417</ymax>
		</bndbox>
		<polygon>
			<x1>323.950618</x1>
			<y1>396.888888</y1>
			<x2>259.950618</x2>
			<y2>407.11111</y2>
			<x3>224.790124</x3>
			<y3>408.888888</y3>
			<x4>221.62963</x4>
			<y4>415.777778</y4>
			<x5>265.481482</x5>
			<y5>409.11111</y5>
			<x6>323.950618</x6>
			<y6>396.888888</y6>
		</polygon>
	</object>
	<object>
		<name>dent</name>
		<pose>Unspecified</pose>
		<truncated>0</truncated>
		<difficult>0</difficult>
		<occluded>0</occluded>
		<bndbox>
			<xmin>268</xmin>
			<xmax>309</xmax>
			<ymin>412</ymin>
			<ymax>419</ymax>
		</bndbox>
		<polygon>
			<x1>286.024692</x1>
			<y1>413.555556</y1>
			<x2>267.45679</x2>
			<y2>418</y2>
			<x3>308.148148</x3>
			<y3>411.11111</y3>
			<x4>286.024692</x4>
			<y4>413.555556</y4>
		</polygon>
	</object>
	<object>
		<name>dent</name>
		<pose>Unspecified</pose>
		<truncated>0</truncated>
		<difficult>0</difficult>
		<occluded>0</occluded>
		<bndbox>
			<xmin>357</xmin>
			<xmax>423</xmax>
			<ymin>509</ymin>
			<ymax>521</ymax>
		</bndbox>
		<polygon>
			<x1>368.592592</x1>
			<y1>520</y1>
			<x2>393.08642</x2>
			<y2>517.11111</y2>
			<x3>422.320988</x3>
			<y3>507.777778</y3>
			<x4>388.74074</x4>
			<y4>514.666666</y4>
			<x5>357.135802</x5>
			<y5>515.777778</y5>
			<x6>355.950618</x6>
			<y6>518.666666</y6>
			<x7>368.592592</x7>
			<y7>520</y7>
		</polygon>
	</object>
	<object>
		<name>dent</name>
		<pose>Unspecified</pose>
		<truncated>0</truncated>
		<difficult>0</difficult>
		<occluded>0</occluded>
		<bndbox>
			<xmin>360</xmin>
			<xmax>412</xmax>
			<ymin>545</ymin>
			<ymax>555</ymax>
		</bndbox>
		<polygon>
			<x1>373.728396</x1>
			<y1>554.444444</y1>
			<x2>395.851852</x2>
			<y2>550.888888</y2>
			<x3>411.25926</x3>
			<y3>544.444444</y3>
			<x4>389.135802</x4>
			<y4>549.11111</y4>
			<x5>372.938272</x5>
			<y5>549.333334</y5>
			<x6>359.111112</x6>
			<y6>552.666666</y6>
			<x7>373.728396</x7>
			<y7>554.444444</y7>
		</polygon>
	</object>
	<object>
		<name>dent</name>
		<pose>Unspecified</pose>
		<truncated>0</truncated>
		<difficult>0</difficult>
		<occluded>0</occluded>
		<bndbox>
			<xmin>149</xmin>
			<xmax>211</xmax>
			<ymin>569</ymin>
			<ymax>579</ymax>
		</bndbox>
		<polygon>
			<x1>192</x1>
			<y1>570.888888</y1>
			<x2>190.024692</x2>
			<y2>575.11111</y2>
			<x3>150.123456</x3>
			<y3>571.777778</y3>
			<x4>148.148148</x4>
			<y4>573.777778</y4>
			<x5>197.925926</x5>
			<y5>578</y5>
			<x6>209.777778</x6>
			<y6>573.777778</y6>
			<x7>178.962962</x7>
			<y7>568.444444</y7>
			<x8>156.049382</x8>
			<y8>569.11111</y8>
			<x9>192</x9>
			<y9>570.888888</y9>
		</polygon>
	</object>
	<object>
		<name>dent</name>
		<pose>Unspecified</pose>
		<truncated>0</truncated>
		<difficult>0</difficult>
		<occluded>0</occluded>
		<bndbox>
			<xmin>270</xmin>
			<xmax>332</xmax>
			<ymin>603</ymin>
			<ymax>622</ymax>
		</bndbox>
		<polygon>
			<x1>331.061728</x1>
			<y1>618.99631</y1>
			<x2>307.753086</x2>
			<y2>612.551866</y2>
			<x3>293.925926</x3>
			<y3>609.8852</y3>
			<x4>296.691358</x4>
			<y4>607.218534</y4>
			<x5>330.271604</x5>
			<y5>610.551866</y5>
			<x6>276.54321</x6>
			<y6>602.329644</y6>
			<x7>276.54321</x7>
			<y7>604.329644</y7>
			<x8>288.395062</x8>
			<y8>606.329644</y8>
			<x9>282.469136</x9>
			<y9>611.218534</y9>
			<x10>270.222222</x10>
			<y10>609.440756</y10>
			<x11>268.641976</x11>
			<y11>614.329644</y11>
			<x12>291.555556</x12>
			<y12>613.440756</y12>
			<x13>292.74074</x13>
			<y13>611.440756</y13>
			<x14>327.111112</x14>
			<y14>621.440756</y14>
			<x15>331.061728</x15>
			<y15>618.99631</y15>
		</polygon>
	</object>
</annotation>
